wikimediaci_utils/__init__.py
wikimediaci_utils/py.typed
wikimediaci_utils-1.3.0.dist-info/COPYING
wikimediaci_utils-1.3.0.dist-info/METADATA
wikimediaci_utils-1.3.0.dist-info/WHEEL
wikimediaci_utils-1.3.0.dist-info/top_level.txt
wikimediaci_utils-1.3.0.dist-info/RECORD
