Metadata-Version: 2.1
Name: wikimediaci_utils
Version: 1.3.0
Summary: Common utility functions for tools related to Wikimedia CI
Home-page: https://gerrit.wikimedia.org/g/integration/utils
Author: Kunal Mehta
Author-email: legoktm@debian.org
License: GPL-3.0-or-later
Requires-Python: >=3.7
License-File: COPYING
Requires-Dist: pyyaml
Requires-Dist: requests
